CHANGES.txt
COPYRIGHT.txt
LICENSE.txt
bootstrap.py
buildout.cfg
setup.py
src/z3c/__init__.py
src/z3c.extfile.egg-info/PKG-INFO
src/z3c.extfile.egg-info/SOURCES.txt
src/z3c.extfile.egg-info/dependency_links.txt
src/z3c.extfile.egg-info/namespace_packages.txt
src/z3c.extfile.egg-info/not-zip-safe
src/z3c.extfile.egg-info/requires.txt
src/z3c.extfile.egg-info/top_level.txt
src/z3c/extfile/README.txt
src/z3c/extfile/SETUP.cfg
src/z3c/extfile/__init__.py
src/z3c/extfile/adapter.py
src/z3c/extfile/adapter.txt
src/z3c/extfile/configure.zcml
src/z3c/extfile/datamanager.py
src/z3c/extfile/filter.py
src/z3c/extfile/filter.txt
src/z3c/extfile/hashdir.py
src/z3c/extfile/hashdir.txt
src/z3c/extfile/interfaces.py
src/z3c/extfile/meta.zcml
src/z3c/extfile/namespace.py
src/z3c/extfile/namespace.txt
src/z3c/extfile/namespace.zcml
src/z3c/extfile/processor.py
src/z3c/extfile/processor.txt
src/z3c/extfile/property.py
src/z3c/extfile/property.txt
src/z3c/extfile/schema.py
src/z3c/extfile/testing.py
src/z3c/extfile/testing.txt
src/z3c/extfile/tests.py
src/z3c/extfile/todo.txt
src/z3c/extfile/utility.py
src/z3c/extfile/z3c.extfile-configure.zcml
src/z3c/extfile/zcml.py
src/z3c/extfile/zcml.txt
src/z3c/extfile/browser/__init__.py
src/z3c/extfile/browser/configure.zcml
src/z3c/extfile/browser/views.py
src/z3c/extfile/browser/widget.py
src/z3c/extfile/browser/widget.txt
src/z3c/extfile/file/SETUP.cfg
src/z3c/extfile/file/__init__.py
src/z3c/extfile/file/configure.zcml
src/z3c/extfile/file/file.py
src/z3c/extfile/file/file.txt
src/z3c/extfile/file/interfaces.py
src/z3c/extfile/file/tests.py
src/z3c/extfile/file/z3c.extfile.file-configure.zcml
src/z3c/extfile/file/browser/__init__.py
src/z3c/extfile/file/browser/configure.zcml
src/z3c/extfile/file/browser/views.py
src/z3c/extfile/testdata/input1.inp
src/z3c/extfile/testdata/paste.ini