Metadata-Version: 1.0
Name: z3c.extfile
Version: 0.3.0b2
Summary: Large file handling for zope3
Home-page: http://svn.zope.org/z3c.extfile
Author: Zope Contributors
Author-email: zope3-dev@zope.org
License: ZPL 2.1
Keywords: zope3 external file
Platform: UNKNOWN
Classifier: Development Status :: 4 - Beta
Classifier: License :: OSI Approved :: Zope Public License
